vardbg/__init__.py
vardbg/__main__.py
vardbg/ansi.py
vardbg/assets/fonts/FiraMono-Bold.ttf
vardbg/assets/fonts/FiraMono-Regular.ttf
vardbg/assets/fonts/Inter-Bold.ttf
vardbg/assets/fonts/Inter-Regular.ttf
vardbg/data.py
vardbg/debugger.py
vardbg/diff_processor.py
vardbg/internal.py
vardbg/main.py
vardbg/output/__init__.py
vardbg/output/console_writer.py
vardbg/output/json_writer.py
vardbg/output/output_delegate.py
vardbg/output/video_writer/__init__.py
vardbg/output/video_writer/config.py
vardbg/output/video_writer/default_config.toml
vardbg/output/video_writer/encoder.py
vardbg/output/video_writer/gif_encoder.py
vardbg/output/video_writer/opencv_encoder.py
vardbg/output/video_writer/renderer.py
vardbg/output/video_writer/text_format.py
vardbg/output/video_writer/text_painter.py
vardbg/output/video_writer/webp_encoder.py
vardbg/output/video_writer/writer.py
vardbg/output/writer.py
vardbg/profiler.py
vardbg/render.py
vardbg/replayer.py
vardbg/tracer.py
vardbg-0.11.6.dist-info/entry_points.txt
vardbg-0.11.6.dist-info/LICENSE
vardbg-0.11.6.dist-info/WHEEL
vardbg-0.11.6.dist-info/METADATA
vardbg-0.11.6.dist-info/RECORD
