Metadata-Version: 2.1
Name: vardbg
Version: 0.11.6
Summary: A simple Python debugger and profiler that generates animated visualizations of program flow.
Home-page: https://github.com/CCExtractor/vardbg
License: MIT
Keywords: debug,debugger,visualization
Author: Danny Lin
Author-email: danny@kdrag0n.dev
Requires-Python: >=3.6,<4.0
Classifier: Development Status :: 3 - Alpha
Classifier: Environment :: Console
Classifier: Intended Audience :: Developers
Classifier: License :: OSI Approved :: MIT License
Classifier: Operating System :: OS Independent
Classifier: Programming Language :: Python :: 3
Classifier: Programming Language :: Python :: 3.6
Classifier: Programming Language :: Python :: 3.7
Classifier: Programming Language :: Python :: 3.8
Classifier: Topic :: Software Development
Classifier: Topic :: Software Development :: Debuggers
Requires-Dist: click (>=7.0,<8.0)
Requires-Dist: colorama (>=0.4.3,<0.5.0)
Requires-Dist: dictdiffer (>=0.8.1,<0.9.0)
Requires-Dist: imageio (>=2.6.1,<3.0.0)
Requires-Dist: jsonpickle (>=1.2,<2.0)
Requires-Dist: opencv-python (>=4.1.2,<5.0.0)
Requires-Dist: pillow (>=7.0.0,<8.0.0)
Requires-Dist: pygments (>=2.5.2,<3.0.0)
Requires-Dist: sortedcontainers (>=2.1.0,<3.0.0)
Requires-Dist: toml (>=0.10.0,<0.11.0)
Project-URL: Bug Tracker, https://github.com/CCExtractor/vardbg/issues
Project-URL: Documentation, https://github.com/CCExtractor/vardbg/blob/master/README.md
Project-URL: Repository, https://github.com/CCExtractor/vardbg
